MANIFEST.in
README.rst
setup.py
collective/__init__.py
collective.portletpage.egg-info/PKG-INFO
collective.portletpage.egg-info/SOURCES.txt
collective.portletpage.egg-info/dependency_links.txt
collective.portletpage.egg-info/entry_points.txt
collective.portletpage.egg-info/namespace_packages.txt
collective.portletpage.egg-info/not-zip-safe
collective.portletpage.egg-info/requires.txt
collective.portletpage.egg-info/top_level.txt
collective/portletpage/__init__.py
collective/portletpage/config.py
collective/portletpage/configure.zcml
collective/portletpage/content.py
collective/portletpage/interfaces.py
collective/portletpage/portlets.py
collective/portletpage/rebuildAllPo.sh
collective/portletpage/browser/__init__.py
collective/portletpage/browser/column.py
collective/portletpage/browser/configure.zcml
collective/portletpage/browser/icon.gif
collective/portletpage/browser/interfaces.py
collective/portletpage/browser/manage-portletpage-portlets.pt
collective/portletpage/browser/portletpage-column.pt
collective/portletpage/browser/portletpage.css
collective/portletpage/browser/portletpage.py
collective/portletpage/browser/two-columns.pt
collective/portletpage/i18n/plone-es.po
collective/portletpage/i18n/plone-it.po
collective/portletpage/i18n/plone-manual.pot
collective/portletpage/i18n/plone.pot
collective/portletpage/locales/collective.portletpage-manual.pot
collective/portletpage/locales/collective.portletpage.pot
collective/portletpage/locales/de/LC_MESSAGES/collective.portletpage.mo
collective/portletpage/locales/de/LC_MESSAGES/collective.portletpage.po
collective/portletpage/locales/es/LC_MESSAGES/collective.portletpage.mo
collective/portletpage/locales/es/LC_MESSAGES/collective.portletpage.po
collective/portletpage/locales/fr/LC_MESSAGES/collective.portletpage.mo
collective/portletpage/locales/fr/LC_MESSAGES/collective.portletpage.po
collective/portletpage/locales/it/LC_MESSAGES/collective.portletpage.mo
collective/portletpage/locales/it/LC_MESSAGES/collective.portletpage.po
collective/portletpage/profiles/default/actions.xml
collective/portletpage/profiles/default/factorytool.xml
collective/portletpage/profiles/default/metadata.xml
collective/portletpage/profiles/default/portlets.xml
collective/portletpage/profiles/default/rolemap.xml
collective/portletpage/profiles/default/tinymce.xml
